pg4j/__init__.py
pg4j/__main__.py
pg4j/classes.py
pg4j/cli/__init__.py
pg4j/cli/main.py
pg4j/cli/settings.py
pg4j/cli/styles.py
pg4j/cli/typer_options.py
pg4j/dump.py
pg4j/importer.py
pg4j/inputs.py
pg4j/mapper.py
pg4j/settings.py
pg4j/sql.py
pg4j/utils.py
pg4j/version.py
pg4j-0.1.4.dist-info/LICENSE
pg4j-0.1.4.dist-info/METADATA
pg4j-0.1.4.dist-info/WHEEL
pg4j-0.1.4.dist-info/entry_points.txt
pg4j-0.1.4.dist-info/RECORD
